cloudcamp/aws_runtime/__init__.py
cloudcamp/aws_runtime/py.typed
cloudcamp/aws_runtime/_jsii/__init__.py
cloudcamp/aws_runtime/_jsii/aws-runtime@0.0.1.jsii.tgz
cloudcamp.aws_runtime-0.0.1.dist-info/LICENSE
cloudcamp.aws_runtime-0.0.1.dist-info/METADATA
cloudcamp.aws_runtime-0.0.1.dist-info/WHEEL
cloudcamp.aws_runtime-0.0.1.dist-info/top_level.txt
cloudcamp.aws_runtime-0.0.1.dist-info/RECORD
