Metadata-Version: 2.1
Name: cloudcamp.aws-runtime
Version: 0.0.1
Summary: CloudCamp - Launch faster by building scalable infrastructure in few lines of code.
Home-page: https://cloudcamphq.com
Author: Markus Ecker<markus.ecker@gmail.com>
License: MIT
Project-URL: Source, https://github.com/cloudcamphq/cloudcamp.git
Platform: UNKNOWN
Classifier: Intended Audience :: Developers
Classifier: Operating System :: OS Independent
Classifier: Programming Language :: JavaScript
Classifier: Programming Language :: Python :: 3 :: Only
Classifier: Programming Language :: Python :: 3.6
Classifier: Programming Language :: Python :: 3.7
Classifier: Programming Language :: Python :: 3.8
Classifier: Programming Language :: Python :: 3.9
Classifier: Typing :: Typed
Classifier: Development Status :: 4 - Beta
Classifier: License :: OSI Approved
Requires-Python: >=3.6
Requires-Dist: aws-cdk-lib (==2.1.0)
Requires-Dist: constructs (==10.0.12)
Requires-Dist: jsii (<2.0.0,>=1.49.0)
Requires-Dist: publication (>=0.0.3)
